moltrack/__init__.py
moltrack/_widget.py
moltrack/napari.yaml
moltrack/GUI/__init__.py
moltrack/GUI/gui.py
moltrack/GUI/widget_ui.py
moltrack/_tests/__init__.py
moltrack/_tests/test_widget.py
moltrack/dev/cell_render.py
moltrack/funcs/__init__.py
moltrack/funcs/bactfit_utils.py
moltrack/funcs/cell_events.py
moltrack/funcs/cell_heatmap_utils.py
moltrack/funcs/compute_utils.py
moltrack/funcs/diffusion_utils.py
moltrack/funcs/events_utils.py
moltrack/funcs/export_utils.py
moltrack/funcs/import_utils.py
moltrack/funcs/loc_filter_utils.py
moltrack/funcs/management_utils.py
moltrack/funcs/oufti_utils.py
moltrack/funcs/picasso_detect_utils.py
moltrack/funcs/picasso_render_utils.py
moltrack/funcs/pixstats_utils.py
moltrack/funcs/segmentation_events.py
moltrack/funcs/segmentation_utils.py
moltrack/funcs/traces_utils.py
moltrack/funcs/track_filter_utils.py
moltrack/funcs/tracking_utils.py
moltrack/funcs/trackplot_utils.py
moltrack/funcs/trackstats_utils.py
moltrack/funcs/transform_utils.py
napari_moltrack-0.1.9.dist-info/licenses/LICENSE
pygpufit/Gpufit.dll
pygpufit/__init__.py
pygpufit/gpufit.py
pygpufit/version.py
napari_moltrack-0.1.9.dist-info/METADATA
napari_moltrack-0.1.9.dist-info/WHEEL
napari_moltrack-0.1.9.dist-info/entry_points.txt
napari_moltrack-0.1.9.dist-info/top_level.txt
napari_moltrack-0.1.9.dist-info/RECORD
